docstring_gen/__init__.py
docstring_gen/_cli.py
docstring_gen/_modidx.py
docstring_gen/docstring_generator.py
docstring_gen-0.4.0.dist-info/LICENSE
docstring_gen-0.4.0.dist-info/METADATA
docstring_gen-0.4.0.dist-info/WHEEL
docstring_gen-0.4.0.dist-info/entry_points.txt
docstring_gen-0.4.0.dist-info/top_level.txt
docstring_gen-0.4.0.dist-info/RECORD
