Metadata-Version: 2.1
Name: docstring-gen
Version: 0.4.0
Summary: Generate docstrings using OpenAI's Codex model.
Home-page: https://github.com/airtai/docstring-gen
Author: airt
Author-email: info@airt.ai
License: Apache Software License 2.0
Keywords: nbdev jupyter notebook python mkdocs material docstring generator
Platform: UNKNOWN
Classifier: Development Status :: 4 - Beta
Classifier: Intended Audience :: Developers
Classifier: Natural Language :: English
Classifier: Programming Language :: Python :: 3.8
Classifier: Programming Language :: Python :: 3.9
Classifier: Programming Language :: Python :: 3.10
Classifier: License :: OSI Approved :: Apache Software License
Requires-Python: >=3.8
License-File: LICENSE
Requires-Dist: nbformat >=5.7.1
Requires-Dist: typer[all] >=0.7.0
Requires-Dist: openai ==0.27.2
Requires-Dist: mypy-extensions ==1.0.0
Provides-Extra: dev
Requires-Dist: nbdev-mkdocs ==0.2.2 ; extra == 'dev'
Requires-Dist: bandit ==1.7.4 ; extra == 'dev'
Requires-Dist: semgrep ==1.61.1 ; extra == 'dev'
Requires-Dist: pytest ==7.2.1 ; extra == 'dev'
Requires-Dist: black ==23.1.0 ; extra == 'dev'
Requires-Dist: mypy ==1.0.1 ; extra == 'dev'
Requires-Dist: mkdocs ==1.4.2 ; extra == 'dev'
Requires-Dist: mkdocstrings[python] ==0.20.0 ; extra == 'dev'
Requires-Dist: mkdocs-material ==9.1.1 ; extra == 'dev'
Requires-Dist: mkdocs-literate-nav ==0.6.0 ; extra == 'dev'
Requires-Dist: mkdocs-section-index ==0.3.5 ; extra == 'dev'
Requires-Dist: configupdater ==3.1.1 ; extra == 'dev'
Requires-Dist: griffe ==0.24.1 ; extra == 'dev'
Requires-Dist: ruamel.yaml ==0.17.21 ; extra == 'dev'
Requires-Dist: playwright ==1.32.0 ; extra == 'dev'
Requires-Dist: pre-commit ==2.21.0 ; extra == 'dev'
Requires-Dist: detect-secrets ==1.4.0 ; extra == 'dev'
